matrixlib_jfj/__init__.py
matrixlib_jfj/__main__.py
matrixlib_jfj/matrix.py
matrixlib_jfj/utils.py
matrixlib_jfj/vector.py
matrixlib_jfj-0.2.5.dist-info/LICENSE.md
matrixlib_jfj-0.2.5.dist-info/METADATA
matrixlib_jfj-0.2.5.dist-info/WHEEL
matrixlib_jfj-0.2.5.dist-info/top_level.txt
matrixlib_jfj-0.2.5.dist-info/RECORD
